engineer_investor_portfolio-0.1.0.dist-info/licenses/LICENSE
portfolio_analysis/__init__.py
portfolio_analysis/analysis/__init__.py
portfolio_analysis/analysis/montecarlo.py
portfolio_analysis/analysis/optimization.py
portfolio_analysis/analysis/portfolio.py
portfolio_analysis/data/__init__.py
portfolio_analysis/data/loader.py
portfolio_analysis/metrics/__init__.py
portfolio_analysis/metrics/benchmark.py
portfolio_analysis/metrics/performance.py
portfolio_analysis/utils/__init__.py
portfolio_analysis/utils/helpers.py
portfolio_analysis/visualization/__init__.py
portfolio_analysis/visualization/interactive.py
portfolio_analysis/visualization/plots.py
engineer_investor_portfolio-0.1.0.dist-info/METADATA
engineer_investor_portfolio-0.1.0.dist-info/WHEEL
engineer_investor_portfolio-0.1.0.dist-info/top_level.txt
engineer_investor_portfolio-0.1.0.dist-info/RECORD
