Metadata-Version: 2.4
Name: engineer-investor-portfolio
Version: 0.1.0
Summary: Professional portfolio analysis tools for DIY investors
Author-email: Engineer Investor <egr.investor@gmail.com>
License: MIT
Project-URL: Homepage, https://github.com/engineerinvestor/Portfolio-Analysis
Project-URL: Documentation, https://github.com/engineerinvestor/Portfolio-Analysis#readme
Project-URL: Repository, https://github.com/engineerinvestor/Portfolio-Analysis
Project-URL: Issues, https://github.com/engineerinvestor/Portfolio-Analysis/issues
Project-URL: Twitter, https://twitter.com/egr_investor
Keywords: portfolio,investing,finance,analysis,monte-carlo,optimization,stocks,etf
Classifier: Development Status :: 4 - Beta
Classifier: Intended Audience :: Financial and Insurance Industry
Classifier: Intended Audience :: Science/Research
Classifier: License :: OSI Approved :: MIT License
Classifier: Operating System :: OS Independent
Classifier: Programming Language :: Python :: 3
Classifier: Programming Language :: Python :: 3.8
Classifier: Programming Language :: Python :: 3.9
Classifier: Programming Language :: Python :: 3.10
Classifier: Programming Language :: Python :: 3.11
Classifier: Programming Language :: Python :: 3.12
Classifier: Topic :: Office/Business :: Financial :: Investment
Classifier: Topic :: Scientific/Engineering :: Mathematics
Requires-Python: >=3.8
License-File: LICENSE
Requires-Dist: pandas>=1.3.0
Requires-Dist: numpy>=1.20.0
Requires-Dist: yfinance>=0.2.0
Requires-Dist: matplotlib>=3.5.0
Provides-Extra: optimization
Requires-Dist: scipy>=1.7.0; extra == "optimization"
Provides-Extra: interactive
Requires-Dist: ipywidgets>=7.6.0; extra == "interactive"
Provides-Extra: streamlit
Requires-Dist: streamlit>=1.20.0; extra == "streamlit"
Requires-Dist: plotly>=5.10.0; extra == "streamlit"
Requires-Dist: scipy>=1.7.0; extra == "streamlit"
Provides-Extra: dev
Requires-Dist: pytest>=7.0.0; extra == "dev"
Requires-Dist: pytest-cov>=3.0.0; extra == "dev"
Requires-Dist: black>=22.0.0; extra == "dev"
Requires-Dist: ruff>=0.1.0; extra == "dev"
Provides-Extra: all
Requires-Dist: portfolio-analysis[dev,interactive,optimization,streamlit]; extra == "all"
Dynamic: license-file
